<!DOCTYPE ui:UiBinder SYSTEM "http://dl.google.com/gwt/DTD/xhtml.ent">
<ui:UiBinder xmlns:ui="urn:ui:com.google.gwt.uibinder"
	xmlns:g="urn:import:com.google.gwt.user.client.ui" xmlns:v="urn:import:com.christophdietze.jack.client.view">
	<ui:style>
		.inline {
			display: inline;
		}
	</ui:style>
	<g:HTMLPanel>
		<g:HTML ui:field="statusLabel" />
		<br />
		<v:MyAnchor ui:field="signInLink" text="Sign in as guest" />
		<v:MyAnchor ui:field="signOutLink" text="Sign out" />
		<br /><br />
		<v:MyAnchor ui:field="seekLink" text="Seek for Match" />
		<g:HTMLPanel ui:field="seekRunningPanel">
			Seek running
		</g:HTMLPanel>

		<v:MyAnchor ui:field="abortMatchLink" text="Abort Match" />
	</g:HTMLPanel>
</ui:UiBinder> 
